{"metadata": {"filename": "00000671bw.tif", "height": 384, "width": 256}, "xml": {"TextRegion": {"generic": [], "paragraph": [[[119, 35], [119, 137], [24, 137], [24, 35]], [[224, 36], [224, 195], [128, 195], [128, 36]]], "caption": [[[118, 295], [118, 303], [23, 303], [23, 295]]], "page-number": [[[127, 321], [127, 323], [121, 323], [121, 321]]], "footer": [[[153, 341], [153, 348], [6, 348], [6, 341]]]}, "ImageRegion": {"generic": [[[118, 142], [118, 282], [24, 282], [24, 142]]]}, "GraphicRegion": {"generic": []}}}